mdtob64/__init__.py
mdtob64/mdtob64.py
mdtob64-0.0.4.dist-info/LICENSE.txt
mdtob64-0.0.4.dist-info/METADATA
mdtob64-0.0.4.dist-info/WHEEL
mdtob64-0.0.4.dist-info/entry_points.txt
mdtob64-0.0.4.dist-info/top_level.txt
mdtob64-0.0.4.dist-info/RECORD
