Metadata-Version: 2.1
Name: mdtob64
Version: 0.0.4
Summary: markdown图片转换base64程序
Home-page: 
Author: 测码范晔
Author-email: 1538379200@qq.com
License: UNKNOWN
Platform: UNKNOWN
Classifier: Programming Language :: Python :: 3
Classifier: License :: OSI Approved :: MIT License
Classifier: Operating System :: OS Independent
License-File: LICENSE.txt
